{
  "section": "A066",
  "section_name": "第A066版",
  "title": "特朗普发出威胁：\n　　“下一个是古巴”",
  "url": "https://mdaily.hangzhou.com.cn/dskb/2026/03/29/article_detail_2_20260329A066.html",
  "date": "2026-03-29",
  "relative_url": "article_detail_2_20260329A066.html",
  "author": "",
  "publish_date": "2026-03-29",
  "content": "都市快报-特朗普发出威胁：\n　　“下一个是古巴” \r\n     \r\n     \r\n     \r\n    \r\n    \r\n    \r\n    \r\n    \r\n    \r\n \r\n \r\n\t \r\n\t     \r\n\t          \r\n\t    \t 特朗普发出威胁：\n　　“下一个是古巴” \r\n\t          \r\n\t        \n\n\r\n\t        \n2026-03-29\n\r\n\t     \r\n\t     \r\n\t        \t\t \r\n\t        \t\t \r\n\t        \t\t \r\n\t\t\t        \t\n\n\r\n\t       \n\n　　继美国对委内瑞拉和伊朗采取军事行动之后，美国总统特朗普3月27日对古巴发出威胁，称“下一个是古巴”。\n\n　　特朗普当天在佛罗里达州迈阿密举行的一场会议上说：“顺便提一句，下一个是古巴……非常感谢。古巴是下一个。”\n\n　　美国今年年初对委内瑞拉发动大规模军事打击后，进一步加大对古巴的压力，包括实施新一轮石油限制措施。特朗普本月15日宣称，将“先解决伊朗，然后是古巴”。\n\n　　古巴外交部副部长德科西奥在美国媒体22日播出的采访中表示，古巴军队正为美国可能发起的军事侵略做准备。\n\n　　伊朗称打击美军藏匿地点\n\n　　造成“极其严重”伤亡\n\n　　据伊朗媒体28日报道，伊朗武装部队哈塔姆安比亚中央总部发言人说，对总共超过500名美军聚集的两个据点进行了打击，造成“极其严重”的伤亡。\n\n　　发言人说，过去数小时内，美军两个藏匿点被定位。第一个藏匿点位于阿联酋迪拜，聚集超400人；第二个藏匿点聚集超100人。这两个地点均被伊朗伊斯兰革命卫队使用精确制导导弹和无人机锁定并打击，造成了“极其严重”的伤亡。\n\n　　发言人称：“救护车已连续数小时忙于转运死伤者，其中包括美国指挥官和士兵。”\n\n　　伊朗此前指责，美军士兵逃离军事基地，躲进酒店和办公场所。此举是在用周边国家的平民做“人盾”。\n\n　　一名美国国防部官员3月27日透露，自针对伊朗的作战行动开始以来，截至当日，已有303名美军现役人员受伤，这一数字高于国防部本周早些时候通报的大约290人。在这些伤员中，已有273人重返岗位。目前仍有10名美军现役人员身受重伤。此外，已有13名美军现役人员在行动中阵亡。",
  "word_count": 957
}